rng_rava/__init__.py
rng_rava/rava_defs.py
rng_rava/rava_rng.py
rng_rava/rava_rng_aio.py
rng_rava/rava_rng_led.py
rng_rava/acq/__init__.py
rng_rava/acq/acq_tools.py
rng_rava/acq/rava_acquisition.py
rng_rava/tk/__init__.py
rng_rava/tk/rava.png
rng_rava/tk/rava_app.py
rng_rava/tk/rava_cfg.py
rng_rava/tk/rava_subapp.py
rng_rava/tk/acq/__init__.py
rng_rava/tk/acq/__main__.py
rng_rava/tk/acq/rava_subapp_acquisition.py
rng_rava/tk/acq/win_progress.py
rng_rava/tk/ctrlp/__init__.py
rng_rava/tk/ctrlp/__main__.py
rng_rava/tk/ctrlp/rava_subapp_control_panel.py
rng_rava-2.0.0.dist-info/LICENSE
rng_rava-2.0.0.dist-info/METADATA
rng_rava-2.0.0.dist-info/WHEEL
rng_rava-2.0.0.dist-info/top_level.txt
rng_rava-2.0.0.dist-info/RECORD
