Metadata-Version: 2.1
Name: rng_rava
Version: 2.0.0
Summary: Python driver for the RAVA RNG device
Author-email: Gabriel Guerrer <gabrielguerrer@gmail.com>
Project-URL: Homepage, https://github.com/gabrielguerrer/rng_rava_driver_py
Classifier: Programming Language :: Python :: 3
Classifier: License :: OSI Approved :: MIT License
Classifier: Operating System :: OS Independent
Requires-Python: >=3.7
License-File: LICENSE
Requires-Dist: pyserial
Requires-Dist: numpy
